qdrantsync.py
QdrantSync-0.1.0.dist-info/LICENSE
QdrantSync-0.1.0.dist-info/METADATA
QdrantSync-0.1.0.dist-info/WHEEL
QdrantSync-0.1.0.dist-info/entry_points.txt
QdrantSync-0.1.0.dist-info/top_level.txt
QdrantSync-0.1.0.dist-info/RECORD
