Metadata-Version: 2.2
Name: QdrantSync
Version: 0.1.0
Summary: A powerful and flexible CLI tool to migrate data between Qdrant instances.
Author-email: Francisco Jimenez Cabrera <jkfran@gmail.com>
License: MIT License
Keywords: qdrant,migration,sync,cli
Classifier: Programming Language :: Python :: 3
Classifier: Operating System :: OS Independent
Classifier: License :: OSI Approved :: MIT License
Requires-Python: >=3.7
License-File: LICENSE
Requires-Dist: click>=8.1.8
Requires-Dist: qdrant-client>=1.12.2
Requires-Dist: tqdm>=4.67.1
